{
	"name": "OOLINE_Dataset",
	"properties": {
		"linkedServiceName": {
			"referenceName": "AzurePostgreSql",
			"type": "LinkedServiceReference"
		},
		"folder": {
			"name": "Postgres/PostgreSQL - Targets/Sales Schema"
		},
		"annotations": [],
		"type": "AzurePostgreSqlTable",
		"schema": [
			{
				"name": "CONO",
				"type": "smallint",
				"precision": 0,
				"scale": 0
			},
			{
				"name": "ORNO",
				"type": "text",
				"precision": 0,
				"scale": 0
			},
			{
				"name": "PONR",
				"type": "integer",
				"precision": 0,
				"scale": 0
			},
			{
				"name": "POSX",
				"type": "smallint",
				"precision": 0,
				"scale": 0
			},
			{
				"name": "DIVI",
				"type": "text",
				"precision": 0,
				"scale": 0
			},
			{
				"name": "LTYP",
				"type": "text",
				"precision": 0,
				"scale": 0
			},
			{
				"name": "ORST",
				"type": "text",
				"precision": 0,
				"scale": 0
			},
			{
				"name": "FACI",
				"type": "text",
				"precision": 0,
				"scale": 0
			},
			{
				"name": "WHLO",
				"type": "text",
				"precision": 0,
				"scale": 0
			},
			{
				"name": "ITNO",
				"type": "text",
				"precision": 0,
				"scale": 0
			},
			{
				"name": "REPI",
				"type": "text",
				"precision": 0,
				"scale": 0
			},
			{
				"name": "ITDS",
				"type": "text",
				"precision": 0,
				"scale": 0
			},
			{
				"name": "TEDS",
				"type": "text",
				"precision": 0,
				"scale": 0
			},
			{
				"name": "ORQT",
				"type": "numeric",
				"precision": 21,
				"scale": 6
			},
			{
				"name": "ORQA",
				"type": "numeric",
				"precision": 21,
				"scale": 6
			},
			{
				"name": "RNQT",
				"type": "numeric",
				"precision": 21,
				"scale": 6
			},
			{
				"name": "RNQA",
				"type": "numeric",
				"precision": 21,
				"scale": 6
			},
			{
				"name": "ALQT",
				"type": "numeric",
				"precision": 21,
				"scale": 6
			},
			{
				"name": "ALQA",
				"type": "numeric",
				"precision": 21,
				"scale": 6
			},
			{
				"name": "PLQT",
				"type": "numeric",
				"precision": 21,
				"scale": 6
			},
			{
				"name": "PLQA",
				"type": "numeric",
				"precision": 21,
				"scale": 6
			},
			{
				"name": "DLQT",
				"type": "numeric",
				"precision": 21,
				"scale": 6
			},
			{
				"name": "DLQA",
				"type": "numeric",
				"precision": 21,
				"scale": 6
			},
			{
				"name": "IVQT",
				"type": "numeric",
				"precision": 21,
				"scale": 6
			},
			{
				"name": "IVQA",
				"type": "numeric",
				"precision": 21,
				"scale": 6
			},
			{
				"name": "DCCD",
				"type": "smallint",
				"precision": 0,
				"scale": 0
			},
			{
				"name": "ALUN",
				"type": "text",
				"precision": 0,
				"scale": 0
			},
			{
				"name": "DCCA",
				"type": "smallint",
				"precision": 0,
				"scale": 0
			},
			{
				"name": "COFA",
				"type": "numeric",
				"precision": 24,
				"scale": 9
			},
			{
				"name": "DMCF",
				"type": "smallint",
				"precision": 0,
				"scale": 0
			},
			{
				"name": "SPUN",
				"type": "text",
				"precision": 0,
				"scale": 0
			},
			{
				"name": "PCOF",
				"type": "numeric",
				"precision": 24,
				"scale": 9
			},
			{
				"name": "DCCS",
				"type": "smallint",
				"precision": 0,
				"scale": 0
			},
			{
				"name": "COFS",
				"type": "numeric",
				"precision": 24,
				"scale": 9
			},
			{
				"name": "DMCS",
				"type": "smallint",
				"precision": 0,
				"scale": 0
			},
			{
				"name": "POPN",
				"type": "text",
				"precision": 0,
				"scale": 0
			},
			{
				"name": "ALWT",
				"type": "smallint",
				"precision": 0,
				"scale": 0
			},
			{
				"name": "ALWQ",
				"type": "text",
				"precision": 0,
				"scale": 0
			},
			{
				"name": "SAPR",
				"type": "numeric",
				"precision": 23,
				"scale": 6
			},
			{
				"name": "NEPR",
				"type": "numeric",
				"precision": 23,
				"scale": 6
			},
			{
				"name": "SACD",
				"type": "integer",
				"precision": 0,
				"scale": 0
			},
			{
				"name": "PRMO",
				"type": "text",
				"precision": 0,
				"scale": 0
			},
			{
				"name": "DIC1",
				"type": "smallint",
				"precision": 0,
				"scale": 0
			},
			{
				"name": "DIC2",
				"type": "smallint",
				"precision": 0,
				"scale": 0
			},
			{
				"name": "DIC3",
				"type": "smallint",
				"precision": 0,
				"scale": 0
			},
			{
				"name": "DIC4",
				"type": "smallint",
				"precision": 0,
				"scale": 0
			},
			{
				"name": "DIC5",
				"type": "smallint",
				"precision": 0,
				"scale": 0
			},
			{
				"name": "DIC6",
				"type": "smallint",
				"precision": 0,
				"scale": 0
			},
			{
				"name": "DIP1",
				"type": "numeric",
				"precision": 7,
				"scale": 2
			},
			{
				"name": "DIP2",
				"type": "numeric",
				"precision": 7,
				"scale": 2
			},
			{
				"name": "DIP3",
				"type": "numeric",
				"precision": 7,
				"scale": 2
			},
			{
				"name": "DIP4",
				"type": "numeric",
				"precision": 7,
				"scale": 2
			},
			{
				"name": "DIP5",
				"type": "numeric",
				"precision": 7,
				"scale": 2
			},
			{
				"name": "DIP6",
				"type": "numeric",
				"precision": 7,
				"scale": 2
			},
			{
				"name": "DIA1",
				"type": "numeric",
				"precision": 21,
				"scale": 4
			},
			{
				"name": "DIA2",
				"type": "numeric",
				"precision": 21,
				"scale": 4
			},
			{
				"name": "DIA3",
				"type": "numeric",
				"precision": 21,
				"scale": 4
			},
			{
				"name": "DIA4",
				"type": "numeric",
				"precision": 21,
				"scale": 4
			},
			{
				"name": "DIA5",
				"type": "numeric",
				"precision": 21,
				"scale": 4
			},
			{
				"name": "DIA6",
				"type": "numeric",
				"precision": 21,
				"scale": 4
			},
			{
				"name": "CMP1",
				"type": "text",
				"precision": 0,
				"scale": 0
			},
			{
				"name": "CMP2",
				"type": "text",
				"precision": 0,
				"scale": 0
			},
			{
				"name": "CMP3",
				"type": "text",
				"precision": 0,
				"scale": 0
			},
			{
				"name": "CMP4",
				"type": "text",
				"precision": 0,
				"scale": 0
			},
			{
				"name": "CMP5",
				"type": "text",
				"precision": 0,
				"scale": 0
			},
			{
				"name": "CMP6",
				"type": "text",
				"precision": 0,
				"scale": 0
			},
			{
				"name": "DIBE",
				"type": "text",
				"precision": 0,
				"scale": 0
			},
			{
				"name": "DIRE",
				"type": "text",
				"precision": 0,
				"scale": 0
			},
			{
				"name": "DCHA",
				"type": "smallint",
				"precision": 0,
				"scale": 0
			},
			{
				"name": "DPST",
				"type": "smallint",
				"precision": 0,
				"scale": 0
			},
			{
				"name": "DDSU",
				"type": "smallint",
				"precision": 0,
				"scale": 0
			},
			{
				"name": "IDSC",
				"type": "smallint",
				"precision": 0,
				"scale": 0
			},
			{
				"name": "ACRF",
				"type": "text",
				"precision": 0,
				"scale": 0
			},
			{
				"name": "OTDI",
				"type": "smallint",
				"precision": 0,
				"scale": 0
			},
			{
				"name": "DWDT",
				"type": "integer",
				"precision": 0,
				"scale": 0
			},
			{
				"name": "DWHM",
				"type": "smallint",
				"precision": 0,
				"scale": 0
			},
			{
				"name": "CODT",
				"type": "integer",
				"precision": 0,
				"scale": 0
			},
			{
				"name": "COHM",
				"type": "smallint",
				"precision": 0,
				"scale": 0
			},
			{
				"name": "DWDZ",
				"type": "integer",
				"precision": 0,
				"scale": 0
			},
			{
				"name": "DWHZ",
				"type": "smallint",
				"precision": 0,
				"scale": 0
			},
			{
				"name": "CODZ",
				"type": "integer",
				"precision": 0,
				"scale": 0
			},
			{
				"name": "COHZ",
				"type": "smallint",
				"precision": 0,
				"scale": 0
			},
			{
				"name": "TIZO",
				"type": "text",
				"precision": 0,
				"scale": 0
			},
			{
				"name": "DLTS",
				"type": "smallint",
				"precision": 0,
				"scale": 0
			},
			{
				"name": "STCD",
				"type": "smallint",
				"precision": 0,
				"scale": 0
			},
			{
				"name": "PRCH",
				"type": "smallint",
				"precision": 0,
				"scale": 0
			},
			{
				"name": "RORC",
				"type": "smallint",
				"precision": 0,
				"scale": 0
			},
			{
				"name": "RORN",
				"type": "text",
				"precision": 0,
				"scale": 0
			},
			{
				"name": "RORL",
				"type": "integer",
				"precision": 0,
				"scale": 0
			},
			{
				"name": "UCOS",
				"type": "numeric",
				"precision": 23,
				"scale": 6
			},
			{
				"name": "COCD",
				"type": "integer",
				"precision": 0,
				"scale": 0
			},
			{
				"name": "UCCD",
				"type": "smallint",
				"precision": 0,
				"scale": 0
			},
			{
				"name": "CMNO",
				"type": "text",
				"precision": 0,
				"scale": 0
			},
			{
				"name": "HDPR",
				"type": "text",
				"precision": 0,
				"scale": 0
			},
			{
				"name": "CFIN",
				"type": "bigint",
				"precision": 0,
				"scale": 0
			},
			{
				"name": "ECVS",
				"type": "smallint",
				"precision": 0,
				"scale": 0
			},
			{
				"name": "VTCD",
				"type": "smallint",
				"precision": 0,
				"scale": 0
			},
			{
				"name": "JDCD",
				"type": "text",
				"precision": 0,
				"scale": 0
			},
			{
				"name": "DLSP",
				"type": "text",
				"precision": 0,
				"scale": 0
			},
			{
				"name": "LNAM",
				"type": "numeric",
				"precision": 17,
				"scale": 2
			},
			{
				"name": "LNA2",
				"type": "numeric",
				"precision": 17,
				"scale": 2
			},
			{
				"name": "DINR",
				"type": "integer",
				"precision": 0,
				"scale": 0
			},
			{
				"name": "DISX",
				"type": "smallint",
				"precision": 0,
				"scale": 0
			},
			{
				"name": "AGNO",
				"type": "text",
				"precision": 0,
				"scale": 0
			},
			{
				"name": "BAGC",
				"type": "text",
				"precision": 0,
				"scale": 0
			},
			{
				"name": "BAGD",
				"type": "integer",
				"precision": 0,
				"scale": 0
			},
			{
				"name": "AGLN",
				"type": "integer",
				"precision": 0,
				"scale": 0
			},
			{
				"name": "PRRF",
				"type": "text",
				"precision": 0,
				"scale": 0
			},
			{
				"name": "NTCD",
				"type": "smallint",
				"precision": 0,
				"scale": 0
			},
			{
				"name": "CNQT",
				"type": "numeric",
				"precision": 21,
				"scale": 6
			},
			{
				"name": "EDFP",
				"type": "numeric",
				"precision": 23,
				"scale": 6
			},
			{
				"name": "SMCD",
				"type": "text",
				"precision": 0,
				"scale": 0
			},
			{
				"name": "BNCD",
				"type": "smallint",
				"precision": 0,
				"scale": 0
			},
			{
				"name": "PRAC",
				"type": "smallint",
				"precision": 0,
				"scale": 0
			},
			{
				"name": "VRCD",
				"type": "text",
				"precision": 0,
				"scale": 0
			},
			{
				"name": "ECLC",
				"type": "text",
				"precision": 0,
				"scale": 0
			},
			{
				"name": "ORCO",
				"type": "text",
				"precision": 0,
				"scale": 0
			},
			{
				"name": "PRTX",
				"type": "bigint",
				"precision": 0,
				"scale": 0
			},
			{
				"name": "POTX",
				"type": "bigint",
				"precision": 0,
				"scale": 0
			},
			{
				"name": "DTID",
				"type": "bigint",
				"precision": 0,
				"scale": 0
			},
			{
				"name": "DELS",
				"type": "smallint",
				"precision": 0,
				"scale": 0
			},
			{
				"name": "E0PA",
				"type": "text",
				"precision": 0,
				"scale": 0
			},
			{
				"name": "DSGP",
				"type": "text",
				"precision": 0,
				"scale": 0
			},
			{
				"name": "MOYE",
				"type": "text",
				"precision": 0,
				"scale": 0
			},
			{
				"name": "PUSN",
				"type": "text",
				"precision": 0,
				"scale": 0
			},
			{
				"name": "PUTP",
				"type": "smallint",
				"precision": 0,
				"scale": 0
			},
			{
				"name": "QTQL",
				"type": "smallint",
				"precision": 0,
				"scale": 0
			},
			{
				"name": "TEPA",
				"type": "text",
				"precision": 0,
				"scale": 0
			},
			{
				"name": "PACT",
				"type": "text",
				"precision": 0,
				"scale": 0
			},
			{
				"name": "CUPA",
				"type": "text",
				"precision": 0,
				"scale": 0
			},
			{
				"name": "D1QT",
				"type": "numeric",
				"precision": 21,
				"scale": 6
			},
			{
				"name": "CUNO",
				"type": "text",
				"precision": 0,
				"scale": 0
			},
			{
				"name": "CUOR",
				"type": "text",
				"precision": 0,
				"scale": 0
			},
			{
				"name": "CUPO",
				"type": "integer",
				"precision": 0,
				"scale": 0
			},
			{
				"name": "CUSX",
				"type": "smallint",
				"precision": 0,
				"scale": 0
			},
			{
				"name": "SMCC",
				"type": "smallint",
				"precision": 0,
				"scale": 0
			},
			{
				"name": "RSCD",
				"type": "text",
				"precision": 0,
				"scale": 0
			},
			{
				"name": "MUFT",
				"type": "smallint",
				"precision": 0,
				"scale": 0
			},
			{
				"name": "INPR",
				"type": "numeric",
				"precision": 23,
				"scale": 6
			},
			{
				"name": "CUCT",
				"type": "text",
				"precision": 0,
				"scale": 0
			},
			{
				"name": "ABNO",
				"type": "smallint",
				"precision": 0,
				"scale": 0
			},
			{
				"name": "PROJ",
				"type": "text",
				"precision": 0,
				"scale": 0
			},
			{
				"name": "ELNO",
				"type": "text",
				"precision": 0,
				"scale": 0
			},
			{
				"name": "BPAT",
				"type": "text",
				"precision": 0,
				"scale": 0
			},
			{
				"name": "BPST",
				"type": "smallint",
				"precision": 0,
				"scale": 0
			},
			{
				"name": "NOAA",
				"type": "smallint",
				"precision": 0,
				"scale": 0
			},
			{
				"name": "CPRE",
				"type": "text",
				"precision": 0,
				"scale": 0
			},
			{
				"name": "HAFE",
				"type": "text",
				"precision": 0,
				"scale": 0
			},
			{
				"name": "CAWE",
				"type": "numeric",
				"precision": 21,
				"scale": 6
			},
			{
				"name": "WHSL",
				"type": "text",
				"precision": 0,
				"scale": 0
			},
			{
				"name": "BANO",
				"type": "text",
				"precision": 0,
				"scale": 0
			},
			{
				"name": "CAMU",
				"type": "text",
				"precision": 0,
				"scale": 0
			},
			{
				"name": "ADID",
				"type": "text",
				"precision": 0,
				"scale": 0
			},
			{
				"name": "ROUT",
				"type": "text",
				"precision": 0,
				"scale": 0
			},
			{
				"name": "RODN",
				"type": "smallint",
				"precision": 0,
				"scale": 0
			},
			{
				"name": "DSDT",
				"type": "integer",
				"precision": 0,
				"scale": 0
			},
			{
				"name": "DSHM",
				"type": "smallint",
				"precision": 0,
				"scale": 0
			},
			{
				"name": "DSTX",
				"type": "text",
				"precision": 0,
				"scale": 0
			},
			{
				"name": "DEFC",
				"type": "smallint",
				"precision": 0,
				"scale": 0
			},
			{
				"name": "PLDT",
				"type": "integer",
				"precision": 0,
				"scale": 0
			},
			{
				"name": "PLHM",
				"type": "smallint",
				"precision": 0,
				"scale": 0
			},
			{
				"name": "SRCD",
				"type": "smallint",
				"precision": 0,
				"scale": 0
			},
			{
				"name": "SPLC",
				"type": "text",
				"precision": 0,
				"scale": 0
			},
			{
				"name": "DLBU",
				"type": "smallint",
				"precision": 0,
				"scale": 0
			},
			{
				"name": "SPOS",
				"type": "smallint",
				"precision": 0,
				"scale": 0
			},
			{
				"name": "FDED",
				"type": "integer",
				"precision": 0,
				"scale": 0
			},
			{
				"name": "LDED",
				"type": "integer",
				"precision": 0,
				"scale": 0
			},
			{
				"name": "AETY",
				"type": "smallint",
				"precision": 0,
				"scale": 0
			},
			{
				"name": "ATNR",
				"type": "bigint",
				"precision": 0,
				"scale": 0
			},
			{
				"name": "SCMO",
				"type": "text",
				"precision": 0,
				"scale": 0
			},
			{
				"name": "PRPR",
				"type": "smallint",
				"precision": 0,
				"scale": 0
			},
			{
				"name": "CINA",
				"type": "smallint",
				"precision": 0,
				"scale": 0
			},
			{
				"name": "ATV1",
				"type": "numeric",
				"precision": 21,
				"scale": 6
			},
			{
				"name": "ATV2",
				"type": "numeric",
				"precision": 21,
				"scale": 6
			},
			{
				"name": "ATV3",
				"type": "numeric",
				"precision": 21,
				"scale": 6
			},
			{
				"name": "ATV4",
				"type": "numeric",
				"precision": 21,
				"scale": 6
			},
			{
				"name": "ATV5",
				"type": "numeric",
				"precision": 21,
				"scale": 6
			},
			{
				"name": "ATV6",
				"type": "text",
				"precision": 0,
				"scale": 0
			},
			{
				"name": "ATV7",
				"type": "text",
				"precision": 0,
				"scale": 0
			},
			{
				"name": "ATV8",
				"type": "text",
				"precision": 0,
				"scale": 0
			},
			{
				"name": "ATV9",
				"type": "text",
				"precision": 0,
				"scale": 0
			},
			{
				"name": "ATV0",
				"type": "text",
				"precision": 0,
				"scale": 0
			},
			{
				"name": "CNNR",
				"type": "bigint",
				"precision": 0,
				"scale": 0
			},
			{
				"name": "MNIN",
				"type": "text",
				"precision": 0,
				"scale": 0
			},
			{
				"name": "REPN",
				"type": "bigint",
				"precision": 0,
				"scale": 0
			},
			{
				"name": "ATPR",
				"type": "text",
				"precision": 0,
				"scale": 0
			},
			{
				"name": "ATMO",
				"type": "text",
				"precision": 0,
				"scale": 0
			},
			{
				"name": "ORTY",
				"type": "text",
				"precision": 0,
				"scale": 0
			},
			{
				"name": "SUNO",
				"type": "text",
				"precision": 0,
				"scale": 0
			},
			{
				"name": "PUPR",
				"type": "numeric",
				"precision": 23,
				"scale": 6
			},
			{
				"name": "PUCD",
				"type": "integer",
				"precision": 0,
				"scale": 0
			},
			{
				"name": "PPUN",
				"type": "text",
				"precision": 0,
				"scale": 0
			},
			{
				"name": "CUCD",
				"type": "text",
				"precision": 0,
				"scale": 0
			},
			{
				"name": "ODI1",
				"type": "numeric",
				"precision": 7,
				"scale": 2
			},
			{
				"name": "ODI2",
				"type": "numeric",
				"precision": 7,
				"scale": 2
			},
			{
				"name": "ODI3",
				"type": "numeric",
				"precision": 7,
				"scale": 2
			},
			{
				"name": "OURR",
				"type": "text",
				"precision": 0,
				"scale": 0
			},
			{
				"name": "OURT",
				"type": "text",
				"precision": 0,
				"scale": 0
			},
			{
				"name": "BUYE",
				"type": "text",
				"precision": 0,
				"scale": 0
			},
			{
				"name": "FWHL",
				"type": "text",
				"precision": 0,
				"scale": 0
			},
			{
				"name": "PRNO",
				"type": "text",
				"precision": 0,
				"scale": 0
			},
			{
				"name": "SCHN",
				"type": "bigint",
				"precision": 0,
				"scale": 0
			},
			{
				"name": "MODL",
				"type": "text",
				"precision": 0,
				"scale": 0
			},
			{
				"name": "TEDL",
				"type": "text",
				"precision": 0,
				"scale": 0
			},
			{
				"name": "TEL2",
				"type": "text",
				"precision": 0,
				"scale": 0
			},
			{
				"name": "RGDT",
				"type": "integer",
				"precision": 0,
				"scale": 0
			},
			{
				"name": "RGTM",
				"type": "integer",
				"precision": 0,
				"scale": 0
			},
			{
				"name": "LMDT",
				"type": "integer",
				"precision": 0,
				"scale": 0
			},
			{
				"name": "CHNO",
				"type": "smallint",
				"precision": 0,
				"scale": 0
			},
			{
				"name": "CHID",
				"type": "text",
				"precision": 0,
				"scale": 0
			},
			{
				"name": "RORX",
				"type": "smallint",
				"precision": 0,
				"scale": 0
			},
			{
				"name": "LMTS",
				"type": "bigint",
				"precision": 0,
				"scale": 0
			},
			{
				"name": "RTQA",
				"type": "numeric",
				"precision": 21,
				"scale": 6
			},
			{
				"name": "RTQT",
				"type": "numeric",
				"precision": 21,
				"scale": 6
			},
			{
				"name": "PRHL",
				"type": "text",
				"precision": 0,
				"scale": 0
			},
			{
				"name": "SERN",
				"type": "text",
				"precision": 0,
				"scale": 0
			},
			{
				"name": "CTNO",
				"type": "text",
				"precision": 0,
				"scale": 0
			},
			{
				"name": "APBA",
				"type": "smallint",
				"precision": 0,
				"scale": 0
			},
			{
				"name": "CFGL",
				"type": "text",
				"precision": 0,
				"scale": 0
			},
			{
				"name": "WATP",
				"type": "text",
				"precision": 0,
				"scale": 0
			},
			{
				"name": "GWTP",
				"type": "text",
				"precision": 0,
				"scale": 0
			},
			{
				"name": "PRHW",
				"type": "text",
				"precision": 0,
				"scale": 0
			},
			{
				"name": "SERW",
				"type": "text",
				"precision": 0,
				"scale": 0
			},
			{
				"name": "PWNR",
				"type": "integer",
				"precision": 0,
				"scale": 0
			},
			{
				"name": "PWSX",
				"type": "smallint",
				"precision": 0,
				"scale": 0
			},
			{
				"name": "EWST",
				"type": "smallint",
				"precision": 0,
				"scale": 0
			},
			{
				"name": "AGNB",
				"type": "text",
				"precision": 0,
				"scale": 0
			},
			{
				"name": "CTNS",
				"type": "text",
				"precision": 0,
				"scale": 0
			},
			{
				"name": "WATQ",
				"type": "smallint",
				"precision": 0,
				"scale": 0
			},
			{
				"name": "TECN",
				"type": "text",
				"precision": 0,
				"scale": 0
			},
			{
				"name": "INAP",
				"type": "text",
				"precision": 0,
				"scale": 0
			},
			{
				"name": "PCNR",
				"type": "integer",
				"precision": 0,
				"scale": 0
			},
			{
				"name": "PCSU",
				"type": "smallint",
				"precision": 0,
				"scale": 0
			},
			{
				"name": "RELI",
				"type": "integer",
				"precision": 0,
				"scale": 0
			},
			{
				"name": "PIDE",
				"type": "text",
				"precision": 0,
				"scale": 0
			},
			{
				"name": "PCLA",
				"type": "numeric",
				"precision": 23,
				"scale": 6
			},
			{
				"name": "BOP1",
				"type": "smallint",
				"precision": 0,
				"scale": 0
			},
			{
				"name": "SCLB",
				"type": "numeric",
				"precision": 17,
				"scale": 2
			},
			{
				"name": "OFNO",
				"type": "text",
				"precision": 0,
				"scale": 0
			},
			{
				"name": "VERS",
				"type": "smallint",
				"precision": 0,
				"scale": 0
			},
			{
				"name": "OFNR",
				"type": "integer",
				"precision": 0,
				"scale": 0
			},
			{
				"name": "OFSX",
				"type": "smallint",
				"precision": 0,
				"scale": 0
			},
			{
				"name": "DECU",
				"type": "text",
				"precision": 0,
				"scale": 0
			},
			{
				"name": "TEPY",
				"type": "text",
				"precision": 0,
				"scale": 0
			},
			{
				"name": "ARST",
				"type": "smallint",
				"precision": 0,
				"scale": 0
			},
			{
				"name": "RSC1",
				"type": "text",
				"precision": 0,
				"scale": 0
			},
			{
				"name": "PMOR",
				"type": "smallint",
				"precision": 0,
				"scale": 0
			},
			{
				"name": "CBSM",
				"type": "smallint",
				"precision": 0,
				"scale": 0
			},
			{
				"name": "INIP",
				"type": "smallint",
				"precision": 0,
				"scale": 0
			},
			{
				"name": "UPAV",
				"type": "smallint",
				"precision": 0,
				"scale": 0
			},
			{
				"name": "QTBC",
				"type": "numeric",
				"precision": 21,
				"scale": 6
			},
			{
				"name": "MPID",
				"type": "smallint",
				"precision": 0,
				"scale": 0
			},
			{
				"name": "TOMU",
				"type": "numeric",
				"precision": 21,
				"scale": 6
			},
			{
				"name": "ENNO",
				"type": "text",
				"precision": 0,
				"scale": 0
			},
			{
				"name": "LNCL",
				"type": "smallint",
				"precision": 0,
				"scale": 0
			},
			{
				"name": "PRIO",
				"type": "smallint",
				"precision": 0,
				"scale": 0
			},
			{
				"name": "CCSA",
				"type": "numeric",
				"precision": 23,
				"scale": 6
			},
			{
				"name": "RAGN",
				"type": "text",
				"precision": 0,
				"scale": 0
			},
			{
				"name": "RASN",
				"type": "text",
				"precision": 0,
				"scale": 0
			},
			{
				"name": "CLAT",
				"type": "text",
				"precision": 0,
				"scale": 0
			},
			{
				"name": "OLSC",
				"type": "smallint",
				"precision": 0,
				"scale": 0
			},
			{
				"name": "MIGI",
				"type": "text",
				"precision": 0,
				"scale": 0
			},
			{
				"name": "PIKD",
				"type": "smallint",
				"precision": 0,
				"scale": 0
			},
			{
				"name": "DPOL",
				"type": "text",
				"precision": 0,
				"scale": 0
			},
			{
				"name": "RSC5",
				"type": "text",
				"precision": 0,
				"scale": 0
			},
			{
				"name": "RSC6",
				"type": "text",
				"precision": 0,
				"scale": 0
			},
			{
				"name": "RSC7",
				"type": "text",
				"precision": 0,
				"scale": 0
			},
			{
				"name": "MPRD",
				"type": "integer",
				"precision": 0,
				"scale": 0
			},
			{
				"name": "UCA1",
				"type": "text",
				"precision": 0,
				"scale": 0
			},
			{
				"name": "UCA2",
				"type": "text",
				"precision": 0,
				"scale": 0
			},
			{
				"name": "UCA3",
				"type": "text",
				"precision": 0,
				"scale": 0
			},
			{
				"name": "UCA4",
				"type": "text",
				"precision": 0,
				"scale": 0
			},
			{
				"name": "UCA5",
				"type": "text",
				"precision": 0,
				"scale": 0
			},
			{
				"name": "UCA6",
				"type": "text",
				"precision": 0,
				"scale": 0
			},
			{
				"name": "UCA7",
				"type": "text",
				"precision": 0,
				"scale": 0
			},
			{
				"name": "UCA8",
				"type": "text",
				"precision": 0,
				"scale": 0
			},
			{
				"name": "UCA9",
				"type": "text",
				"precision": 0,
				"scale": 0
			},
			{
				"name": "UCA0",
				"type": "text",
				"precision": 0,
				"scale": 0
			},
			{
				"name": "UDN1",
				"type": "numeric",
				"precision": 23,
				"scale": 6
			},
			{
				"name": "UDN2",
				"type": "numeric",
				"precision": 23,
				"scale": 6
			},
			{
				"name": "UDN3",
				"type": "numeric",
				"precision": 23,
				"scale": 6
			},
			{
				"name": "UDN4",
				"type": "numeric",
				"precision": 23,
				"scale": 6
			},
			{
				"name": "UDN5",
				"type": "numeric",
				"precision": 23,
				"scale": 6
			},
			{
				"name": "UDN6",
				"type": "numeric",
				"precision": 23,
				"scale": 6
			},
			{
				"name": "UID1",
				"type": "integer",
				"precision": 0,
				"scale": 0
			},
			{
				"name": "UID2",
				"type": "integer",
				"precision": 0,
				"scale": 0
			},
			{
				"name": "UID3",
				"type": "integer",
				"precision": 0,
				"scale": 0
			},
			{
				"name": "UCT1",
				"type": "text",
				"precision": 0,
				"scale": 0
			},
			{
				"name": "accountingEntity",
				"type": "text",
				"precision": 0,
				"scale": 0
			},
			{
				"name": "variationNumber",
				"type": "bigint",
				"precision": 0,
				"scale": 0
			},
			{
				"name": "timestamp",
				"type": "timestamp without time zone",
				"precision": 0,
				"scale": 0
			},
			{
				"name": "deleted",
				"type": "boolean",
				"precision": 0,
				"scale": 0
			},
			{
				"name": "archived",
				"type": "boolean",
				"precision": 0,
				"scale": 0
			}
		],
		"typeProperties": {
			"schema": "public",
			"table": "OOLINE"
		}
	},
	"type": "Microsoft.DataFactory/factories/datasets"
}